pyrandvec.py
pyrandvec-1.0.1.dist-info/LICENSE
pyrandvec-1.0.1.dist-info/METADATA
pyrandvec-1.0.1.dist-info/WHEEL
pyrandvec-1.0.1.dist-info/top_level.txt
pyrandvec-1.0.1.dist-info/RECORD
